dotstat_io/__init__.py
dotstat_io/authentication.py
dotstat_io/client.py
dotstat_io-1.0.7.dist-info/METADATA
dotstat_io-1.0.7.dist-info/WHEEL
dotstat_io-1.0.7.dist-info/RECORD
