Metadata-Version: 2.4
Name: dotstat_io
Version: 1.0.7
Summary: Utility to download or upload data from/to .Stat Suite using ADFS authentication to connect to it
License: MIT
Author: Gyorgy Gyomai
Author-email: gyorgy.gyomai@oecd.org
Requires-Python: >=3.10,<4.0
Classifier: License :: OSI Approved :: MIT License
Classifier: Programming Language :: Python :: 3
Classifier: Programming Language :: Python :: 3.10
Classifier: Programming Language :: Python :: 3.11
Classifier: Programming Language :: Python :: 3.12
Classifier: Programming Language :: Python :: 3.13
Classifier: Programming Language :: Python :: 3.14
Requires-Dist: chardet (>=5.1.0,<6.0.0)
Requires-Dist: msal (>=1.22.0,<2.0.0)
Requires-Dist: requests (>=2.29.0,<3.0.0)
Requires-Dist: requests-kerberos (>=0.14.0,<0.15.0)
Requires-Dist: setuptools (>=75.6.0,<76.0.0)
